koinonikos/__cli__.py
koinonikos/__init__.py
koinonikos/_version.py
koinonikos/conf/__init__.py
koinonikos/conf/about/__init__.yaml
koinonikos/conf/batch/__init__.yaml
koinonikos/conf/config.yaml
koinonikos/conf/dotenv/__init__.yaml
koinonikos/conf/hconf.yaml
koinonikos/conf/hydra/help/help.yaml
koinonikos/conf/hydra/job_logging/custom.yaml
koinonikos/conf/joblib/__init__.yaml
koinonikos/conf/mode/__init__.yaml
koinonikos/conf/mode/debug.yaml
koinonikos/conf/path/__batch__.yaml
koinonikos/conf/path/__default__.yaml
koinonikos/conf/path/__init__.yaml
koinonikos/conf/project/__init__.yaml
koinonikos/conf/task/__init__.yaml
koinonikos/project.toml
koinonikos/py.typed
koinonikos-0.1.1.dist-info/LICENSE
koinonikos-0.1.1.dist-info/METADATA
koinonikos-0.1.1.dist-info/WHEEL
koinonikos-0.1.1.dist-info/entry_points.txt
koinonikos-0.1.1.dist-info/RECORD
